lib_clockifybot/__init__.py
lib_clockifybot/database.py
lib_clockifybot/models_leave/__init__.py
lib_clockifybot/models_leave/base.py
lib_clockifybot/models_leave/identity.py
lib_clockifybot/models_leave/leave.py
lib_clockifybot/models_report/__init__.py
lib_clockifybot/models_report/base.py
lib_clockifybot/models_report/request.py
lib_clockifybot/models_report/team.py
lib_clockifybot/models_report/user_report.py
lib_clockifybot/models_report/workspace.py
lib_clockifybot-3.0.1.dist-info/METADATA
lib_clockifybot-3.0.1.dist-info/WHEEL
lib_clockifybot-3.0.1.dist-info/top_level.txt
lib_clockifybot-3.0.1.dist-info/RECORD
