Metadata-Version: 2.4
Name: lib_clockifybot
Version: 3.0.1
Author: retr0err0r - veininvein
Requires-Dist: psycopg2-binary==2.9.11
Requires-Dist: SQLAlchemy==2.0.45
Dynamic: author
Dynamic: requires-dist
